woopra.py-0.3.0.dist-info/DESCRIPTION.rst
woopra.py-0.3.0.dist-info/METADATA
woopra.py-0.3.0.dist-info/RECORD
woopra.py-0.3.0.dist-info/WHEEL
woopra.py-0.3.0.dist-info/metadata.json
woopra.py-0.3.0.dist-info/top_level.txt
woopra_tracker/__init__.py
