Metadata-Version: 2.0
Name: woopra.py
Version: 0.3.0
Summary: Alternative Woopra integration with Django support
Home-page: https://github.com/bennylope/woopra.py
Author: Ben Lopatin
Author-email: ben@benlopatin.com
License: MIT license
Keywords: woopra
Platform: UNKNOWN
Classifier: Development Status :: 2 - Pre-Alpha
Classifier: Intended Audience :: Developers
Classifier: License :: OSI Approved :: MIT License
Classifier: Natural Language :: English
Classifier: Programming Language :: Python :: 2
Classifier: Programming Language :: Python :: 2.7
Classifier: Programming Language :: Python :: 3
Classifier: Programming Language :: Python :: 3.6
Requires-Dist: requests
